ltsf/__init__.py
ltsf/Trainer/__init__.py
ltsf/Trainer/trainer.py
ltsf/config/__init__.py
ltsf/config/config.py
ltsf/dataset/__init__.py
ltsf/dataset/data_factory.py
ltsf/dataset/data_loader.py
ltsf/layers/AutoCorrelation.py
ltsf/layers/Autoformer_EncDec.py
ltsf/layers/Conv_Blocks.py
ltsf/layers/Crossformer_EncDec.py
ltsf/layers/ETSformer_EncDec.py
ltsf/layers/Embed.py
ltsf/layers/FourierCorrelation.py
ltsf/layers/MultiWaveletCorrelation.py
ltsf/layers/Pyraformer_EncDec.py
ltsf/layers/SelfAttention_Family.py
ltsf/layers/Transformer_EncDec.py
ltsf/layers/__init__.py
ltsf/models/Autoformer.py
ltsf/models/Crossformer.py
ltsf/models/DLinear.py
ltsf/models/ETSformer.py
ltsf/models/FEDformer.py
ltsf/models/FiLM.py
ltsf/models/Informer.py
ltsf/models/LightTS.py
ltsf/models/MICN.py
ltsf/models/Nonstationary_Transformer.py
ltsf/models/PatchTST.py
ltsf/models/Pyraformer.py
ltsf/models/Reformer.py
ltsf/models/TimesNet.py
ltsf/models/Transformer.py
ltsf/models/__init__.py
ltsf/utils/__init__.py
ltsf/utils/masking.py
ltsf/utils/metrics.py
ltsf/utils/timefeatures.py
ltsf/utils/tools.py
ltsf-0.1.dist-info/LICENSE
ltsf-0.1.dist-info/METADATA
ltsf-0.1.dist-info/WHEEL
ltsf-0.1.dist-info/top_level.txt
ltsf-0.1.dist-info/RECORD
