Metadata-Version: 2.1
Name: ltsf
Version: 0.1
Summary: Long-term time-series forecasting package
Home-page: https://github.com/Hank0626/ltsf
Author: Peiyuan Liu
Author-email: hank010626@163.com
Requires-Python: >=3.8.0
License-File: LICENSE
Requires-Dist: torch (==1.12.0)
Requires-Dist: reformer-pytorch
Requires-Dist: tqdm
Requires-Dist: pyyaml
Requires-Dist: requests
Requires-Dist: matplotlib
Requires-Dist: einops (==0.4.0)
Requires-Dist: numpy (==1.23.5)
Requires-Dist: pandas (==1.5.3)
Requires-Dist: scikit-learn (==1.2.2)
Requires-Dist: scipy (==1.10.1)
Requires-Dist: sympy (==1.11.1)
Requires-Dist: patool (==1.12)
Requires-Dist: sktime (==0.16.1)
